microtrade-0.0.1.data/purelib/microtrade/__init__.py
microtrade-0.0.1.data/purelib/microtrade/microtradecmd.pyd
microtrade-0.0.1.dist-info/METADATA
microtrade-0.0.1.dist-info/WHEEL
microtrade-0.0.1.dist-info/top_level.txt
microtrade-0.0.1.dist-info/RECORD
