Metadata-Version: 2.1
Name: microtrade
Version: 0.0.1
Summary: MicroTrade command for Windows
Home-page: UNKNOWN
Author: haohaninfo
Author-email: haohanservice@haohaninfo.com
License: UNKNOWN
Platform: UNKNOWN
Classifier: Programming Language :: Python :: 3.7
Classifier: Programming Language :: Python :: 3.8
Classifier: Operating System :: Microsoft :: Windows
Requires-Dist: requests
